AUTHORS.rst
CONTRIBUTING.rst
HISTORY.rst
LICENSE
MANIFEST.in
README.rst
setup.cfg
setup.py
demo_package/__init__.py
demo_package/cli.py
demo_package/demo_package.py
demo_package.egg-info/PKG-INFO
demo_package.egg-info/SOURCES.txt
demo_package.egg-info/dependency_links.txt
demo_package.egg-info/entry_points.txt
demo_package.egg-info/not-zip-safe
demo_package.egg-info/requires.txt
demo_package.egg-info/top_level.txt
docs/Makefile
docs/authors.rst
docs/conf.py
docs/contributing.rst
docs/history.rst
docs/index.rst
docs/installation.rst
docs/make.bat
docs/readme.rst
docs/usage.rst
tests/.test_demo_package.py.swp
tests/test_demo_package.py